odoo/addons/web_tree_image/README.rst
odoo/addons/web_tree_image/__init__.py
odoo/addons/web_tree_image/__manifest__.py
odoo/addons/web_tree_image/i18n/web_tree_image.pot
odoo/addons/web_tree_image/static/description/icon.png
odoo/addons/web_tree_image/static/src/js/tooltip.js
odoo/addons/web_tree_image/static/src/less/common.less
odoo/addons/web_tree_image/view/assets.xml
odoo11_addon_web_tree_image-11.0.1.0.1.dist-info/METADATA
odoo11_addon_web_tree_image-11.0.1.0.1.dist-info/WHEEL
odoo11_addon_web_tree_image-11.0.1.0.1.dist-info/top_level.txt
odoo11_addon_web_tree_image-11.0.1.0.1.dist-info/RECORD
